[
    "大叔日常学习会②",
    {
        "毕业": 84,
        "快乐": 80,
        "可爱": 67,
        "宝宝": 38,
        "桃子": 23,
        "阿山": 16,
        "YODA": 15,
        "大师": 14,
        "真的": 14,
        "就是": 13,
        "桃桃": 13,
        "设乐": 13,
        "纯爱": 12,
        "米粒": 10,
        "阿桃": 10,
        "喜子": 9,
        "感觉": 9,
        "纯奈": 9,
        "迷离": 9,
        "我要": 9,
        "奥运": 9,
        "日村": 8,
        "莲哥": 8,
        "知道": 8,
        "前程似锦": 8,
        "不是": 8,
        "看到": 7,
        "这个": 7,
        "已经": 7,
        "这么": 7,
        "自知之明": 7,
        "大叔": 7,
        "感謝組": 7,
        "阿鸟": 7,
        "节目": 6,
        "模仿": 6,
        "什么": 6,
        "好像": 6,
        "山下": 6,
        "美月": 6,
        "确实": 6,
        "喜欢": 6,
        "呜呜": 6,
        "果然": 6,
        "纯奶": 6,
        "放弃": 6,
        "莲糖": 6,
        "自己": 5,
        "一样": 5,
        "自我": 5,
        "是不是": 5,
        "一席话": 5,
        "三期": 5,
        "妈妈": 5,
        "二期": 5,
        "突然": 5,
        "厉害": 5,
        "不愧": 5,
        "绪儿": 5,
        "长高": 5,
        "偶像": 5,
        "看过": 4,
        "成功": 4,
        "奥运会": 4,
        "毕竟": 4,
        "村子": 4,
        "那个": 4,
        "这里": 4,
        "身高": 4,
        "这是": 4,
        "开始": 4,
        "承包": 4,
        "表情": 4,
        "吐舌": 4,
        "鸟儿": 4,
        "人间": 4,
        "田村": 4,
        "好好": 4,
        "认罪": 3,
        "整活": 3,
        "隧道": 3,
        "大佬": 3,
        "辛苦": 3,
        "歌名": 3,
        "工事": 3,
        "一脸": 3,
        "不准": 3,
        "主任": 3,
        "TAMA": 3,
        "这些": 3,
        "原来": 3,
        "同步": 3,
        "高能": 3,
        "还是": 3,
        "声音": 3,
        "MAYU": 3,
        "记得": 3,
        "引进": 3,
        "心动": 3,
        "怎么": 3,
        "运营": 3,
        "这部": 3,
        "亲亲": 3,
        "飞鸟": 3,
        "镜头": 3,
        "忏悔": 3,
        "空姐": 3,
        "孩子": 3,
        "今年": 3,
        "年少": 3,
        "所以": 3,
        "可愛": 3,
        "就算": 3,
        "肘哥": 3,
        "差不多": 3,
        "大福": 3,
        "一次": 3,
        "这样": 3,
        "笑容": 3,
        "想起": 3,
        "老婆": 3,
        "高高": 3,
        "优等生": 3,
        "谐星": 3,
        "儿童": 3,
        "表演": 3,
        "表示": 3,
        "来看": 3,
        "天天": 3,
        "草草": 3,
        "太强": 3,
        "意思": 3,
        "两次": 3,
        "莲宝": 3,
        "快樂": 3,
        "不争": 3
    }
]