[
    "乃木坂跨期分组对抗战②&28单选拔发表",
    {
        "恭喜": 120,
        "可爱": 63,
        "喜子": 62,
        "音音": 61,
        "这个": 52,
        "选拔": 46,
        "一样": 42,
        "贝贝": 41,
        "动作": 40,
        "挂桥": 38,
        "嫂子": 37,
        "贺喜": 34,
        "毕业": 32,
        "不是": 30,
        "YODA": 28,
        "最后": 28,
        "肘哥": 27,
        "三期": 27,
        "花花": 24,
        "真的": 24,
        "加油": 22,
        "二期": 21,
        "大师": 21,
        "阿梅": 20,
        "宝宝": 20,
        "四期": 20,
        "就是": 19,
        "小南": 18,
        "感謝組": 17,
        "快乐": 17,
        "设乐": 16,
        "表情": 16,
        "飞鸟": 16,
        "呜呜": 16,
        "前面": 15,
        "师傅": 15,
        "肯定": 15,
        "可以": 15,
        "一个": 15,
        "飞机": 14,
        "阿山": 14,
        "美月": 14,
        "知道": 14,
        "裙子": 14,
        "确实": 14,
        "这么": 13,
        "兰兰": 13,
        "终于": 13,
        "杀猪": 13,
        "没有": 13,
        "已经": 12,
        "开始": 12,
        "偶像": 12,
        "现在": 12,
        "真夏": 12,
        "完全": 12,
        "好好": 12,
        "贺喜遥香": 11,
        "毕竟": 11,
        "一期": 11,
        "专业": 11,
        "那个": 11,
        "喜欢": 10,
        "福神": 10,
        "老年人": 10,
        "什么": 10,
        "阿鸟": 10,
        "遥香": 9,
        "乌梅": 9,
        "你们": 9,
        "问题": 9,
        "BBA": 9,
        "还是": 9,
        "好看": 9,
        "团员": 9,
        "印象": 9,
        "只有": 8,
        "开心": 8,
        "妈妈": 8,
        "企划": 8,
        "搞笑": 8,
        "孩子": 8,
        "成员": 8,
        "回来": 8,
        "賀喜": 8,
        "中间": 7,
        "永远": 7,
        "第一": 7,
        "简单": 7,
        "运营": 7,
        "结尾": 7,
        "觉得": 7,
        "可能": 7,
        "团队": 7,
        "直接": 7,
        "乃木坂": 7,
        "以前": 7,
        "铁血": 7,
        "小鸟": 7,
        "喜皇": 7,
        "登基": 7,
        "日奈": 7,
        "时候": 7,
        "大家": 7,
        "护法": 7,
        "這個": 7,
        "TEN": 7,
        "小可爱": 7,
        "不愧": 7,
        "心疼": 6,
        "不好": 6,
        "祖宗": 6,
        "高山": 6,
        "小樱": 6,
        "姿势": 6,
        "左后卫": 6,
        "只是": 6,
        "前方": 6,
        "五期": 6,
        "久保": 6,
        "经典": 6,
        "还有": 6,
        "阿喜": 6,
        "前辈": 6,
        "真是": 6,
        "奥特": 6,
        "高能": 6,
        "与田": 6,
        "KII": 6,
        "麻衣": 6,
        "谐星": 6,
        "但是": 6,
        "KAKKI": 6,
        "履历": 6,
        "女人": 6,
        "可惜": 6,
        "同步": 6,
        "军团": 6,
        "开花": 6,
        "希望": 5,
        "一点": 5,
        "的话": 5,
        "回头": 5,
        "感觉": 5,
        "不能": 5,
        "这组": 5,
        "居然": 5,
        "几个": 5,
        "三个": 5,
        "三排": 5,
        "不会": 5,
        "这样": 5,
        "一致": 5,
        "不错": 5,
        "DEN": 5,
        "这首": 5,
        "绪儿": 5,
        "起飞": 5,
        "掛橋": 5,
        "喜哥": 5,
        "不行": 5,
        "抖音": 5,
        "舞蹈": 5,
        "麦球": 5,
        "兄弟": 5,
        "白白": 5,
        "默契": 5,
        "起来": 5,
        "位置": 5,
        "所以": 5,
        "注意": 5,
        "一起": 5,
        "尤达": 5,
        "想到": 5,
        "太好了": 5,
        "应该": 5,
        "少女": 5,
        "桃子": 5,
        "村子": 5,
        "肘肘": 5,
        "生田": 5,
        "蘭蘭": 4,
        "最好": 4,
        "两单": 4,
        "队长": 4,
        "这里": 4,
        "DD": 4,
        "实力": 4,
        "TOP": 4,
        "四个": 4,
        "优势": 4,
        "飛鳥": 4,
        "伟大": 4,
        "综艺": 4,
        "那么": 4,
        "全员": 4,
        "每个": 4,
        "拍手": 4,
        "上来": 4,
        "MV": 4,
        "阵容": 4,
        "老白": 4,
        "好玩": 4,
        "整活": 4,
        "欺负": 4,
        "有毒": 4,
        "絢音": 4,
        "南黑": 4,
        "大佬": 4,
        "一拳": 4,
        "两个": 4,
        "白骑": 4,
        "平衡": 4,
        "怎么": 4,
        "温柔": 4,
        "這樣": 4,
        "这是": 4,
        "一下": 4,
        "日本": 4,
        "霸王花": 4,
        "自己": 4,
        "书法": 4,
        "私服": 4,
        "绝对": 4,
        "超强": 4,
        "選拔": 4,
        "办法": 4,
        "厉害": 4,
        "明显": 4,
        "举手": 4,
        "四头": 4,
        "实至名归": 4,
        "鸟儿": 4,
        "打架": 4,
        "承包": 4,
        "影响": 4,
        "深刻": 4,
        "JOJO": 4,
        "答案": 4,
        "梅开二度": 4,
        "重心": 4,
        "首歌": 4,
        "组长": 4,
        "其实": 4,
        "果然": 4,
        "优秀": 4,
        "一单": 4,
        "老干部": 4,
        "老大": 4,
        "天下第一": 4,
        "樱樱": 4,
        "裁判": 4,
        "全体": 4,
        "漂亮": 4,
        "未来": 4,
        "一直": 4,
        "稳住": 4,
        "这单": 3,
        "没进": 3,
        "镜头": 3,
        "历史": 3,
        "社长": 3,
        "必须": 3,
        "梅有": 3,
        "估计": 3,
        "只要": 3,
        "战绩": 3,
        "其他人": 3,
        "可怜": 3,
        "天王": 3,
        "莲哥": 3,
        "这队": 3,
        "别人": 3,
        "这次": 3,
        "山下": 3,
        "ISEE": 3,
        "影子": 3,
        "最多": 3,
        "SINGOUT": 3,
        "狂喜": 3,
        "梅澤": 3,
        "舒服": 3,
        "还行": 3,
        "下期": 3,
        "位子": 3,
        "发现": 3,
        "记得": 3,
        "高音": 3,
        "真实": 3,
        "久违": 3,
        "故意": 3,
        "初森": 3,
        "游戏": 3,
        "公式": 3,
        "放弃": 3,
        "以为": 3,
        "少林": 3,
        "看不到": 3,
        "心里": 3,
        "正中": 3,
        "抱球": 3,
        "下去": 3,
        "回放": 3,
        "尖叫": 3,
        "根本": 3,
        "不了": 3,
        "稳定": 3,
        "之前": 3,
        "版本": 3,
        "右手": 3,
        "定位": 3,
        "全是": 3,
        "腹肌": 3,
        "反击": 3,
        "开头": 3,
        "ACE": 3,
        "身高": 3,
        "白给": 3,
        "结果": 3,
        "此时": 3,
        "反应": 3,
        "秋元": 3,
        "有点": 3,
        "当然": 3,
        "变成": 3,
        "很漂亮": 3,
        "唯一": 3,
        "这题": 3,
        "手指": 3,
        "WINK": 3,
        "强行": 3,
        "全福": 3,
        "五头": 3,
        "九头": 3,
        "表示": 3,
        "自信": 3,
        "突然": 3,
        "意外": 3,
        "巧合": 3,
        "少年": 3,
        "一模一样": 3,
        "只能": 3,
        "比較": 3,
        "感覺": 3,
        "少林功夫": 3,
        "时代": 3,
        "白石": 3,
        "一個": 3,
        "傻贝贝": 3,
        "不过": 3,
        "原来": 3,
        "精髓": 3,
        "天山": 3,
        "功夫": 3,
        "教主": 3,
        "乃团": 3,
        "霸王": 3,
        "CENTER": 3,
        "一人": 3,
        "今野": 3,
        "副歌": 3,
        "貝貝飛": 3,
        "機音入": 3,
        "买碟": 3,
        "畢業": 3,
        "反复": 3,
        "没错": 3,
        "武功": 3,
        "RESPECT": 3,
        "成功": 3,
        "日村": 3,
        "团长": 3,
        "二排": 3,
        "为啥": 3,
        "站住": 3,
        "第一个": 3,
        "独占": 3,
        "笨蛋": 3,
        "回眸": 3,
        "指导": 3,
        "要饭": 3,
        "提示": 3,
        "可愛": 3,
        "珠美": 3,
        "为什么": 3,
        "中场": 3,
        "泪目": 3,
        "难道": 3,
        "劣势": 3,
        "梅坐": 3,
        "AYAME": 3,
        "不少": 3,
        "村惠梨香": 3,
        "毛病": 3,
        "起立": 3
    }
]