[
    "主题手机照片展②",
    {
        "可爱": 21,
        "YODA": 19,
        "设乐": 16,
        "大师": 14,
        "这个": 11,
        "这张": 11,
        "好看": 11,
        "真的": 10,
        "日村": 10,
        "表情": 9,
        "不是": 8,
        "久保": 8,
        "妈妈": 8,
        "不愧": 7,
        "真夏": 7,
        "照片": 7,
        "可以": 6,
        "什么": 6,
        "哥哥": 6,
        "音音": 6,
        "奇行": 6,
        "嫂子": 6,
        "害羞": 5,
        "动作": 5,
        "DOGE": 5,
        "就是": 5,
        "自己": 5,
        "偶像": 5,
        "谢谢": 5,
        "这么": 5,
        "嚣张": 5,
        "宝宝": 5,
        "没有": 5,
        "眼睛": 5,
        "有点": 5,
        "那个": 5,
        "还是": 5,
        "乃木坂": 4,
        "后期": 4,
        "工事": 4,
        "不幸": 4,
        "喜子": 4,
        "怎么": 4,
        "飛鳥": 4,
        "小吉": 4,
        "有点像": 4,
        "一个": 4,
        "草草": 4,
        "莲哥": 4,
        "衣服": 4,
        "拍照": 4,
        "三期": 4,
        "喜欢": 4,
        "确实": 4,
        "巨人": 4,
        "感謝組": 4,
        "肩膀": 4,
        "女孩": 4,
        "绝对": 3,
        "相信": 3,
        "乃团": 3,
        "看看": 3,
        "今天": 3,
        "现在": 3,
        "一起": 3,
        "铁血": 3,
        "开心": 3,
        "出来": 3,
        "鸟儿": 3,
        "村子": 3,
        "大佬": 3,
        "BGM": 3,
        "乌梅": 3,
        "贺喜": 3,
        "不信": 3,
        "小鸟": 3,
        "镜头": 3,
        "可能": 3,
        "起来": 3,
        "食人魔": 3,
        "一米": 3,
        "XSWL": 3,
        "遥远": 3,
        "PERFECTHUMAN": 3,
        "素材": 3,
        "理理杏": 3,
        "这是": 3,
        "BY": 3,
        "KAKKI": 3,
        "挂桥": 3,
        "還是": 3,
        "大姐头": 3,
        "记忆": 3,
        "不动": 3,
        "眉毛": 3,
        "IPPON": 3,
        "头子": 3,
        "应该": 3,
        "远藤": 3,
        "原力": 3,
        "一眼": 3,
        "别人": 3,
        "左胸": 3,
        "女人": 3,
        "筷子": 3,
        "哪里": 3
    }
]